net_inventorylib/__init__.py
net_inventorylib-2.1.2.dist-info/LICENSE
net_inventorylib-2.1.2.dist-info/METADATA
net_inventorylib-2.1.2.dist-info/WHEEL
net_inventorylib-2.1.2.dist-info/top_level.txt
net_inventorylib-2.1.2.dist-info/RECORD
