Metadata-Version: 2.1
Name: net-inventorylib
Version: 2.1.2
Summary: Network configuration library
Home-page: https://gitlab.developers.cam.ac.uk/uis/netsys/udn/net-inventorylib
Author: Robert Franklin
Author-email: rcf34@cam.ac.uk
Classifier: Programming Language :: Python :: 3
Classifier: License :: OSI Approved :: MIT License
Classifier: Operating System :: OS Independent
License-File: LICENSE
Requires-Dist: deepops
Requires-Dist: jinja2
Requires-Dist: netaddr
Requires-Dist: pyyaml
